repoqa/__init__.py
repoqa/_version.py
repoqa/compute_score.py
repoqa/data.py
repoqa/metric.py
repoqa/search_needle_function.py
repoqa/utility.py
repoqa/provider/__init__.py
repoqa/provider/anthropic.py
repoqa/provider/base.py
repoqa/provider/google.py
repoqa/provider/hf.py
repoqa/provider/openai.py
repoqa/provider/vllm.py
repoqa/provider/request/__init__.py
repoqa/provider/request/anthropic.py
repoqa/provider/request/google.py
repoqa/provider/request/openai.py
repoqa-0.1.2.dist-info/LICENSE
repoqa-0.1.2.dist-info/METADATA
repoqa-0.1.2.dist-info/WHEEL
repoqa-0.1.2.dist-info/entry_points.txt
repoqa-0.1.2.dist-info/top_level.txt
repoqa-0.1.2.dist-info/RECORD
