Metadata-Version: 2.1
Name: repoqa
Version: 0.1.2
Summary: "RepoQA for Evaluating Long-Context Code Understanding"
Home-page: https://github.com/evalplus/repoqa
License: Apache-2.0
Platform: any
Classifier: Operating System :: OS Independent
Classifier: Programming Language :: Python :: 3
Classifier: License :: OSI Approved :: Apache Software License
Requires-Python: >=3.8
License-File: LICENSE
Requires-Dist: tempdir >=0.7.1
Requires-Dist: appdirs >=1.4.4
Requires-Dist: wget >=3.2
Requires-Dist: fire >=0.6.0
Requires-Dist: nltk >=3.8.1
Requires-Dist: rich >=13.5.2
Requires-Dist: numpy >=1.25.2
Requires-Dist: tree-sitter-languages >=1.10.2
Requires-Dist: transformers >=4.40.0
Requires-Dist: openai >=1.23.2
Requires-Dist: anthropic >=0.25.6
Requires-Dist: google-generativeai >=0.5.2
Requires-Dist: stop-sequencer >=1.2.3
Provides-Extra: vllm
Requires-Dist: vllm >=0.3.3 ; extra == 'vllm'
